data_quality_tool/__init__.py
data_quality_tool/__main__.py
data_quality_tool/scripts.py
data_standards_check-0.2.1.dist-info/LICENSE
data_standards_check-0.2.1.dist-info/METADATA
data_standards_check-0.2.1.dist-info/WHEEL
data_standards_check-0.2.1.dist-info/entry_points.txt
data_standards_check-0.2.1.dist-info/top_level.txt
data_standards_check-0.2.1.dist-info/RECORD
