Metadata-Version: 2.1
Name: data-standards-check
Version: 0.2.1
Summary: A tool to check data quality against predefined standards and generated data standards if needed.
Author-email: "Xifan.Z" <xifanzou42@gmail.com>
License: Apache License
Project-URL: Homepage, https://github.com/xifanzou/data_standards_check
Classifier: Programming Language :: Python :: 3
Classifier: Operating System :: OS Independent
Requires-Python: >=3.6
License-File: LICENSE
Requires-Dist: pandas
